AUTHORS.rst
CONTRIBUTING.rst
HISTORY.rst
MANIFEST.in
README.rst
requirements-tests.txt
requirements.txt
setup.py
Solution.egg-info/PKG-INFO
Solution.egg-info/SOURCES.txt
Solution.egg-info/dependency_links.txt
Solution.egg-info/not-zip-safe
Solution.egg-info/requires.txt
Solution.egg-info/top_level.txt
solution/__init__.py
solution/_compat.py
solution/form.py
solution/formset.py
solution/utils.py
solution/fields/__init__.py
solution/fields/boolean.py
solution/fields/collection.py
solution/fields/color.py
solution/fields/date.py
solution/fields/date_time.py
solution/fields/field.py
solution/fields/number.py
solution/fields/select.py
solution/fields/simple_date.py
solution/fields/splitted_datetime.py
solution/fields/text.py
solution/fields/time.py
solution/fields/file/__init__.py
solution/fields/file/file.py
solution/fields/file/helpers.py
solution/fields/file/image.py
solution/validators/__init__.py
solution/validators/dates.py
solution/validators/form_wide.py
solution/validators/patterns.py
solution/validators/simple.py
solution/validators/validator.py
solution/validators/values.py
tests/__init__.py
tests/test_collections.py
tests/test_fields.py
tests/test_fields_date.py
tests/test_fields_image.py
tests/test_fields_simple_date.py
tests/test_fields_splitted_datetime.py
tests/test_fields_time.py
tests/test_forms.py
tests/test_formsets.py
tests/test_multiselects.py
tests/test_selects.py
tests/test_utils.py
tests/test_validators.py
tests/test_validators_dates.py
tests/test_validators_formwide.py